pulumi_vsphere/__init__.py
pulumi_vsphere/_inputs.py
pulumi_vsphere/_utilities.py
pulumi_vsphere/compute_cluster.py
pulumi_vsphere/compute_cluster_host_group.py
pulumi_vsphere/compute_cluster_vm_affinity_rule.py
pulumi_vsphere/compute_cluster_vm_anti_affinity_rule.py
pulumi_vsphere/compute_cluster_vm_dependency_rule.py
pulumi_vsphere/compute_cluster_vm_group.py
pulumi_vsphere/compute_cluster_vm_host_rule.py
pulumi_vsphere/configuration_profile.py
pulumi_vsphere/content_library.py
pulumi_vsphere/content_library_item.py
pulumi_vsphere/custom_attribute.py
pulumi_vsphere/datacenter.py
pulumi_vsphere/datastore_cluster.py
pulumi_vsphere/datastore_cluster_vm_anti_affinity_rule.py
pulumi_vsphere/distributed_port_group.py
pulumi_vsphere/distributed_virtual_switch.py
pulumi_vsphere/distributed_virtual_switch_pvlan_mapping.py
pulumi_vsphere/dpm_host_override.py
pulumi_vsphere/drs_vm_override.py
pulumi_vsphere/entity_permissions.py
pulumi_vsphere/file.py
pulumi_vsphere/folder.py
pulumi_vsphere/get_compute_cluster.py
pulumi_vsphere/get_compute_cluster_host_group.py
pulumi_vsphere/get_configuration_profile.py
pulumi_vsphere/get_content_library.py
pulumi_vsphere/get_content_library_item.py
pulumi_vsphere/get_custom_attribute.py
pulumi_vsphere/get_datacenter.py
pulumi_vsphere/get_datastore.py
pulumi_vsphere/get_datastore_cluster.py
pulumi_vsphere/get_datastore_stats.py
pulumi_vsphere/get_distributed_virtual_switch.py
pulumi_vsphere/get_dynamic.py
pulumi_vsphere/get_folder.py
pulumi_vsphere/get_guest_os_customization.py
pulumi_vsphere/get_host.py
pulumi_vsphere/get_host_base_images.py
pulumi_vsphere/get_host_pci_device.py
pulumi_vsphere/get_host_thumbprint.py
pulumi_vsphere/get_host_vgpu_profile.py
pulumi_vsphere/get_license.py
pulumi_vsphere/get_network.py
pulumi_vsphere/get_ovf_vm_template.py
pulumi_vsphere/get_policy.py
pulumi_vsphere/get_resource_pool.py
pulumi_vsphere/get_role.py
pulumi_vsphere/get_tag.py
pulumi_vsphere/get_tag_category.py
pulumi_vsphere/get_vapp_container.py
pulumi_vsphere-4.16.2.dist-info/METADATA
pulumi_vsphere-4.16.2.dist-info/WHEEL
pulumi_vsphere-4.16.2.dist-info/top_level.txt
pulumi_vsphere-4.16.2.dist-info/RECORD
